Workbook

Sheet Instructions
B2: ANZ-Aligned Automation Productivity Tracker
B3: 10-day individual automation evaluation — ParaBank demo (https://parabank.parasoft.com/parabank/index.htm)
B5: Legend
B6: Yellow fill, blue text | C6: Cells you (tester) or the evaluator type into. Safe to edit.
B7: Light blue fill | C7: Example row — shows the expected format. Do not delete; add new rows below it.
B8: Black text, no fill | C8: Formulas. Do not overwrite — they recalculate automatically.
B10: How the workbook is organised
B11: Daily Log | C11: Fill in once per day (Day 1–10). Tracks planned vs completed cases, pass/fail counts, hours, flakiness, and blockers.
B12: Test Case Tracker | C12: One row per automated test case. Use the dropdowns for Module, Type, Priority, Complexity, Status and Result. Add rows as you go — validation is pre-applied to row 300.
B13: Lists | C13: Reference lists that power the dropdowns. Leave this sheet alone unless you want to add a new dropdown option.
B14: Productivity Dashboard | C14: Auto-calculated from the two sheets above. Nothing to type here — just read it.
B15: Scorecard | C15: Evaluator fills in a 1–5 rating per criterion at the end of Day 10. Weighted score and banding calculate automatically.
B16: Application Coverage | C16: Run-level results for ParaBank, ACME web profiles, and Android/Appium coverage. Only observed results are recorded; blocked and unrun suites are labeled separately.
B17: Notes
B18: • | C18: This tracker measures volume AND quality together — a high case count with a low pass rate or high flakiness is not strong productivity.
B19: • | C19: The Test Case ID convention is TC-<Module abbreviation>-<3-digit number>, e.g. TC-TRF-001 for a Transfers test.
B20: • | C20: Update the Test Case Tracker as you build each script, not retrospectively — same-day logging gives more accurate velocity data.

Sheet Lists
A1: Module | B1: Test Type | C1: Priority | D1: Complexity | E1: Automation Status | F1: Execution Result | G1: Y/N | H1: Day
A2: Framework | B2: Positive | C2: Critical | D2: Low | E2: Not Started | F2: Pass | G2: Y | H2: 1
A3: Registration | B3: Negative | C3: High | D3: Medium | E3: In Progress | F3: Fail | G3: N | H3: 2
A4: Authentication | B4: Boundary | C4: Medium | D4: High | E4: Automated | F4: Not Run | H4: 3
A5: Accounts | B5: Security | C5: Low | E5: Blocked | F5: Skipped | H5: 4
A6: Transfers | B6: Performance | F6: Flaky | H6: 5
A7: Bill Payment | B7: Regression | H7: 6
A8: Transaction Search | H8: 7
A9: Lending | H9: 8
A10: API-REST | H10: 9
A11: API-SOAP | H11: 10
A12: Cross-Browser
A13: Accessibility
A14: Mocks-Extensions
A15: ACME Web
A16: ACME Mobile
A17: Login & Authentication
A18: Customer Registration
A19: Open new Account
A20: Accounts Overview & Balance
A21: Fund Transfer
A22: ParaBank Mobile

Sheet Daily Log
A1: Day | B1: Date | C1: Theme / Focus Area | D1: Planned Cases | E1: Completed Cases | F1: Passed | G1: Failed | H1: Blocked | I1: Completion % | J1: Pass Rate % | K1: Hours Spent | L1: Flaky Tests Introduced | M1: Flaky Tests Fixed | N1: Defects Logged | O1: Key Risk / Assumption Flagged | P1: Blockers | Q1: Tester Notes
A2: 1 | C2: Framework setup & smoke suite | D2: 8 | E2: 8 | F2: 8 | G2: 0 | H2: 0 | I2: =IFERROR(E2/D2,"") -> 1 | J2: =IFERROR(F2/E2,"") -> 1 | N2: 0 | P2: None for isolated-target acceptance. | Q2: Grouped final headed acceptance results by planned scope day; original per-day dates and hours were not recorded.
A3: 2 | C3: Registration & authentication depth | D3: 18 | E3: 18 | F3: 17 | G3: 1 | H3: 0 | I3: =IFERROR(E3/D3,"") -> 1 | J3: =IFERROR(F3/E3,"") -> 0.94444444 | N3: 0 | O3: Blank phone registration is accepted by ParaBank. | P3: None for isolated-target acceptance. | Q3: Grouped acceptance: one expected application-gap failure.
A4: 3 | C4: Accounts & balances | D4: 15 | E4: 15 | F4: 14 | G4: 1 | H4: 0 | I4: =IFERROR(E4/D4,"") -> 1 | J4: =IFERROR(F4/E4,"") -> 0.93333333 | N4: 0 | O4: ParaBank opens accounts from zero-balance sources. | P4: None for isolated-target acceptance. | Q4: Grouped acceptance: one expected application-gap failure.
A5: 4 | C5: Pay Anyone / fund transfers | D5: 18 | E5: 18 | F5: 12 | G5: 6 | H5: 0 | I5: =IFERROR(E5/D5,"") -> 1 | J5: =IFERROR(F5/E5,"") -> 0.66666667 | N5: 0 | O5: ParaBank accepts invalid amounts and same-account transfers. | P5: None for isolated-target acceptance. | Q5: Grouped acceptance: six expected application-gap failures.
A6: 5 | C6: BPAY-style bill payments | D6: 18 | E6: 18 | F6: 16 | G6: 2 | H6: 0 | I6: =IFERROR(E6/D6,"") -> 1 | J6: =IFERROR(F6/E6,"") -> 0.88888889 | N6: 0 | O6: Negative and overdrawn bill payments mutate account balance. | P6: None for isolated-target acceptance. | Q6: Grouped acceptance: two expected application-gap failures.
A7: 6 | C7: Transaction search & statement reconciliation | D7: 15 | E7: 15 | F7: 14 | G7: 1 | H7: 0 | I7: =IFERROR(E7/D7,"") -> 1 | J7: =IFERROR(F7/E7,"") -> 0.93333333 | N7: 0 | O7: Account activity is oldest-first, not newest-first. | P7: None for isolated-target acceptance. | Q7: Grouped acceptance: one expected application-gap failure.
A8: 7 | C8: Lending journey | D8: 15 | E8: 15 | F8: 15 | G8: 0 | H8: 0 | I8: =IFERROR(E8/D8,"") -> 1 | J8: =IFERROR(F8/E8,"") -> 1 | N8: 0 | P8: None for isolated-target acceptance. | Q8: All lending and flagship journey cases passed.
A9: 8 | C9: REST/SOAP API layer | D9: 22 | E9: 22 | F9: 22 | G9: 0 | H9: 0 | I9: =IFERROR(E9/D9,"") -> 1 | J9: =IFERROR(F9/E9,"") -> 1 | N9: 0 | P9: None for isolated-target acceptance. | Q9: Independent REST/SOAP suite: 22/22 passed.
A10: 9 | C10: Cross-browser, mobile, accessibility & PayID simulation | D10: 15 | E10: 15 | F10: 15 | G10: 0 | H10: 0 | I10: =IFERROR(E10/D10,"") -> 1 | J10: =IFERROR(F10/E10,"") -> 1 | N10: 0 | O10: Accessibility scans record violations; PayID paths are mocked. | P10: None for isolated-target acceptance. | Q10: Headed Chromium, Firefox, and mobile each passed 15/15; Gherkin 4/4 scenarios, 29/29 steps.
A11: 10 | B11: 10 | C11: Current full-suite verification | D11: 144 | E11: 144 | F11: 143 | G11: 1 | H11: 0 | I11: 1 | J11: 0.99305556 | L11: 0 | M11: 0 | N11: 1 | O11: Current single-run verification showed 1 unexpected failure in bill payment negative amount handling. | P11: None for isolated-target acceptance. | Q11: Latest run: 143 passed, 1 failed, 0 skipped, 0 flaky.
C12: TOTAL / ACCEPTANCE SUMMARY | D12: =SUM(D2:D11) -> 288 | E12: =SUM(E2:E11) -> 288 | F12: =SUM(F2:F11) -> 276 | G12: =SUM(G2:G11) -> 12 | H12: =SUM(H2:H11) -> 0 | I12: =IFERROR(E12/D12,"") -> 1 | J12: =IFERROR(F12/E12,"") -> 0.95833333 | L12: =SUM(L2:L11) -> 0 | M12: =SUM(M2:M11) -> 0 | N12: =SUM(N2:N11) -> 1 | Q12: Hours were not tracked. Three full reruns: 399 pass, 33 expected application-gap failures, zero unexpected failures, skips or flakes.

Sheet Test Case Tracker
A1: Test Case ID | B1: Module | C1: Scenario Description | D1: Test Type | E1: Priority | F1: Complexity | G1: Day Assigned | H1: Day Completed | I1: Automation Status | J1: Execution Result | K1: Reusable Component (Y/N) | L1: Defect Raised (Y/N) | M1: Defect ID / Link | N1: Notes
A2: TC-TRF-001 | B2: Transfers | C2: Transfer full available balance between own accounts; verify source hits zero and ledger entries match on both sides. | D2: Boundary | E2: High | F2: Medium | G2: 4 | H2: 4 | I2: Automated | J2: Pass | K2: Y | L2: N | N2: Example row — edit or delete before adding your own.
A3: TC-AUT-001 | B3: Authentication | C3: Login page displays the username and password controls. | D3: Smoke | E3: High | F3: Low | G3: 1 | H3: 1 | I3: Automated | J3: Pass | K3: Y | L3: N | N3: Smoke tagged; Headed desktop acceptance 07/10/2026.
A4: TC-AUT-002 | B4: Authentication | C4: API-seeded customer logs in and reaches account services. | D4: Positive | E4: High | F4: Medium | G4: 1 | H4: 1 | I4: Automated | J4: Pass | K4: Y | L4: N | N4: Smoke tagged; API-seeded; Headed desktop acceptance 07/10/2026.
A5: TC-AUT-003 | B5: Authentication | C5: Reject login with an unknown username. | D5: Negative | E5: High | F5: Low | G5: 1 | H5: 1 | I5: Automated | J5: Pass | K5: Y | L5: N | N5: Smoke tagged; Headed desktop acceptance 07/10/2026.
A6: TC-AUT-004 | B6: Authentication | C6: Reject login with an incorrect password. | D6: Negative | E6: High | F6: Low | G6: 1 | H6: 1 | I6: Automated | J6: Pass | K6: Y | L6: N | N6: Smoke tagged; Headed desktop acceptance 07/10/2026.
A7: TC-AUT-005 | B7: Authentication | C7: Reject login with a blank username. | D7: Negative | E7: High | F7: Low | G7: 1 | H7: 1 | I7: Automated | J7: Pass | K7: Y | L7: N | N7: Smoke tagged; Headed desktop acceptance 07/10/2026.
A8: TC-AUT-006 | B8: Authentication | C8: Reject login with a blank password. | D8: Negative | E8: High | F8: Low | G8: 1 | H8: 1 | I8: Automated | J8: Pass | K8: Y | L8: N | N8: Smoke tagged; Headed desktop acceptance 07/10/2026.
A9: TC-REG-001 | B9: Registration | C9: Registration form exposes all onboarding fields. | D9: Smoke | E9: High | F9: Low | G9: 1 | H9: 1 | I9: Automated | J9: Pass | K9: Y | L9: N | N9: Smoke tagged; Headed desktop acceptance 07/10/2026.
A10: TC-REG-002 | B10: Registration | C10: Register a new customer, confirm automatic sign-in, and verify the default account and balance. | D10: E2E | E10: High | F10: Medium | G10: 1 | H10: 1 | I10: Automated | J10: Pass | K10: Y | L10: N | N10: Smoke tagged; API/UI parity; Headed desktop acceptance 07/10/2026.
A11: TC-REG-003 | B11: Registration | C11: Reject registration when first name is blank. | D11: Negative | E11: High | F11: Low | G11: 2 | H11: 2 | I11: Automated | J11: Pass | K11: Y | L11: N | N11: Data-driven mandatory field; Headed desktop acceptance 07/10/2026.
A12: TC-REG-004 | B12: Registration | C12: Reject registration when last name is blank. | D12: Negative | E12: High | F12: Low | G12: 2 | H12: 2 | I12: Automated | J12: Pass | K12: Y | L12: N | N12: Data-driven mandatory field; Headed desktop acceptance 07/10/2026.
A13: TC-REG-005 | B13: Registration | C13: Reject registration when street address is blank. | D13: Negative | E13: High | F13: Low | G13: 2 | H13: 2 | I13: Automated | J13: Pass | K13: Y | L13: N | N13: Data-driven mandatory field; Headed desktop acceptance 07/10/2026.
... A146: TC-CHN-015 | B146: PayID Simulation | C146: Handle a mocked timeout PayID/NPP payment response. | D146: Integration | E146: High | F146: Medium | G146: 9 | H146: 9 | I146: Automated | J146: Pass | K146: Y | L146: N | N146: Mock simulation; no native ParaBank PayID; Headed desktop acceptance 07/10/2026.

Sheet Productivity Dashboard
A1: Productivity Dashboard | M1: Productivity | N1: Share
A2: Auto-calculated from Daily Log and Test Case Tracker — no manual entry on this sheet. | M2: Pass | N2: =COUNTIF('Test Case Tracker'!J3:J500,"Pass") -> 133
M3: Fail | N3: =COUNTIF('Test Case Tracker'!J3:J500,"Fail") -> 11
A4: Overall Volume | M4: Blocked | N4: =COUNTIF('Test Case Tracker'!I3:I500,"Blocked") -> 0
A5: Total test cases logged | B5: =COUNTA('Test Case Tracker'!A3:A500) -> 144 | M5: Not Run | N5: =COUNTIF('Test Case Tracker'!I3:I500,"Not Started")+COUNTIF('Test Case Tracker'!I3:I500,"Not Run") -> 0
A6: Automated | B6: =COUNTIF('Test Case Tracker'!I3:I500,"Automated") -> 144 | M6: Flaky | N6: =COUNTIF('Test Case Tracker'!J3:J500,"Flaky") -> 0
A7: In Progress | B7: =COUNTIF('Test Case Tracker'!I3:I500,"In Progress") -> 0
A8: Blocked | B8: =COUNTIF('Test Case Tracker'!I3:I500,"Blocked") -> 0
A9: Pass rate (Pass ÷ (Pass + Fail)) | B9: =IFERROR(COUNTIF('Test Case Tracker'!J3:J500,"Pass")/(COUNTIF('Test Case Tracker'!J3:J500,"Pass")+COUNTIF('Test Case Tracker'!J3:J500,"Fail")),0) -> 0.92361111
A10: Flakiness rate (Flaky ÷ Automated) | B10: =IFERROR(COUNTIF('Test Case Tracker'!J3:J500,"Flaky")/COUNTIF('Test Case Tracker'!I3:I500,"Automated"),0) -> 0
A12: Quality
A13: Pass | B13: =COUNTIF('Test Case Tracker'!J3:J500,"Pass") -> 133
A14: Fail | B14: =COUNTIF('Test Case Tracker'!J3:J500,"Fail") -> 11
A15: Flaky | B15: =COUNTIF('Test Case Tracker'!J3:J500,"Flaky") -> 0
A16: Not Run | B16: =COUNTIF('Test Case Tracker'!I3:I500,"Not Started")+COUNTIF('Test Case Tracker'!I3:I500,"Not Run") -> 0
A17: Pass rate (Pass ÷ (Pass + Fail)) | B17: =IFERROR(COUNTIF('Test Case Tracker'!J3:J500,"Pass")/(COUNTIF('Test Case Tracker'!J3:J500,"Pass")+COUNTIF('Test Case Tracker'!J3:J500,"Fail")),0) -> 0.92361111
A18: Flakiness rate (Flaky ÷ Automated) | B18: =IFERROR(COUNTIF('Test Case Tracker'!J3:J500,"Flaky")/COUNTIF('Test Case Tracker'!I3:I500,"Automated"),0) -> 0
A20: By Priority
A21: Critical | B21: =COUNTIF('Test Case Tracker'!E3:E500,"Critical") -> 0
A22: High | B22: =COUNTIF('Test Case Tracker'!E3:E500,"High") -> 115
A23: Medium | B23: =COUNTIF('Test Case Tracker'!E3:E500,"Medium") -> 29
A24: Low | B24: =COUNTIF('Test Case Tracker'!E3:E500,"Low") -> 0
A26: By Complexity
A27: Low | B27: =COUNTIF('Test Case Tracker'!F3:F500,"Low") -> 71
A28: Medium | B28: =COUNTIF('Test Case Tracker'!F3:F500,"Medium") -> 64
A29: High | B29: =COUNTIF('Test Case Tracker'!F3:F500,"High") -> 9
A30: Complexity-weighted volume (L×1 + M×2 + H×3) | B30: =COUNTIF('Test Case Tracker'!F3:F500,"Low")+COUNTIF('Test Case Tracker'!F3:F500,"Medium")*2+COUNTIF('Test Case Tracker'!F3:F500,"High")*3 -> 226
A32: Velocity & Reliability
A33: Average cases completed / day | B33: =IFERROR(AVERAGE('Daily Log'!E2:E10),0) -> 16
A34: Total hours spent | B34: =SUM('Daily Log'!K2:K11) -> 0
A35: Cases per hour | B35: =IF(SUM('Daily Log'!K2:K11)=0,"Not tracked",SUM('Daily Log'!E2:E10)/SUM('Daily Log'!K2:K11)) -> Not tracked
A36: Total flaky tests introduced | B36: =SUM('Daily Log'!L2:L11) -> 0
A37: Total flaky tests fixed | B37: =SUM('Daily Log'!M2:M11) -> 0
A38: Flaky tests remaining open | B38: =MAX(0,SUM('Daily Log'!L2:L11)-SUM('Daily Log'!M2:M11)) -> 0
A39: Total defects logged | B39: =SUM('Daily Log'!N2:N11) -> 1
A41: Design & Reuse
A42: Test cases using a reusable component | B42: =COUNTIF('Test Case Tracker'!K3:K500,"Y") -> 144
A43: Reuse rate (of Automated cases) | B43: =IFERROR(COUNTIF('Test Case Tracker'!K3:K500,"Y")/COUNTIF('Test Case Tracker'!I3:I500,"Automated"),0) -> 1

Sheet Scorecard
A1: Individual Productivity Scorecard
A2: Evaluator fills the Rating column (1–5) at the end of Day 10. Everything else calculates.
A4: Criterion | B4: Weight | C4: Rating (1-5) | D4: Weighted Score | E4: Comments
A5: Velocity (cases completed vs. plan, complexity-adjusted) | B5: 0.25 | D5: =IFERROR(B5*C5,"") -> 0
A6: Quality / first-run pass rate | B6: 0.2 | D6: =IFERROR(B6*C6,"") -> 0
A7: Design & reuse (POM, data-driven, shared utilities) | B7: 0.2 | D7: =IFERROR(B7*C7,"") -> 0
A8: Flakiness discipline (introduced vs. fixed by Day 10) | B8: 0.15 | D8: =IFERROR(B8*C8,"") -> 0
A9: Complex end-to-end capability (chained flagship scenarios) | B9: 0.15 | D9: =IFERROR(B9*C9,"") -> 0
A10: Communication (daily logs, final report clarity) | B10: 0.05 | D10: =IFERROR(B10*C10,"") -> 0
A11: TOTAL | B11: =SUM(B5:B10) -> 1 | D11: =SUM(D5:D10) -> 0
A13: Score out of 5 | B13: =D11 -> 0
A14: Overall Band | B14: =_xlfn.IFS(D11>=4,"Strong",D11>=2.5,"Developing",D11<2.5,"Needs Support") -> Needs Support
A16: Calibration: Strong ≥ 4.00 | Developing 2.50–3.99 | Needs Support < 2.50

Sheet Application Coverage
A1: Application | B1: Automation Suite | C1: Platform / Profile | D1: Planned Cases | E1: Completed | F1: Passed | G1: Failed | H1: Skipped / Blocked | I1: Run Status | J1: Run Date | K1: Observed Result / Notes
A2: ParaBank | B2: Playwright (single worker) | C2: Desktop Chromium | D2: 77 | E2: 73 | F2: 60 | G2: 13 | H2: 4 | I2: Completed with failures/skips | J2: 28/09/2026 | K2: Full run summary: 60 passed, 13 failed, 4 skipped. Public target had validation/server inconsistencies.
A3: ParaBank | B3: Playwright headed parallel | C3: Desktop Chromium | D3: 77 | E3: 0 | F3: 0 | G3: 0 | H3: 77 | I3: Blocked before execution | J3: 28/09/2026 | K3: Preflight stopped the run because the shared public demo returned Cloudflare 1015; no cases executed.
A4: ACME Demo | B4: Playwright web suite (headed) | C4: Desktop Chromium | D4: 4 | E4: 4 | F4: 4 | G4: 0 | H4: 0 | I4: Passed | J4: 28/09/2026 | K4: All four functional, accessibility, API and visual tests passed.
A5: ACME Demo | B5: Playwright web suite (headed) | C5: Playwright iPhone 13 emulation | D5: 4 | E5: 4 | F5: 4 | G5: 0 | H5: 0 | I5: Passed | J5: 28/09/2026 | K5: All four functional, accessibility, API and visual tests passed.
A6: ACME Demo | B6: Playwright web suite (headed) | C6: Playwright Pixel 5 emulation | D6: 4 | E6: 4 | F6: 3 | G6: 1 | H6: 0 | I6: Completed with one failure | J6: 28/09/2026 | K6: Functional, accessibility and API tests passed; dashboard visual snapshot failed.
A7: ACME Demo | B7: Playwright web suite (headed) | C7: Playwright Galaxy S9+ emulation | D7: 4 | E7: 4 | F7: 4 | G7: 0 | H7: 0 | I7: Passed | J7: 28/09/2026 | K7: All four functional, accessibility, API and visual tests passed.
A8: ACME Demo | B8: Playwright web suite (headed) | C8: Playwright iPhone 12 emulation | D8: 4 | E8: 4 | F8: 4 | G8: 0 | H8: 0 | I8: Passed | J8: 28/09/2026 | K8: All four functional, accessibility, API and visual tests passed.
A9: ACME Demo | B9: Playwright web suite (headed) | C9: Playwright Pixel 7 emulation | D9: 4 | E9: 4 | F9: 4 | G9: 0 | H9: 0 | I9: Passed | J9: 28/09/2026 | K9: All four functional, accessibility, API and visual tests passed.
A10: ACME Demo | B10: Playwright web suite total | C10: Six projects / viewport profiles | D10: 24 | E10: 24 | F10: 23 | G10: 1 | H10: 0 | I10: Completed with one failure | J10: 28/09/2026 | K10: Latest headed run: 23 passed, 1 failed.
A11: ACME Demo | B11: WebdriverIO + Appium | C11: Android Chrome ? Pixel_10_Pro_Fold (emulator-5554) | D11: 1 | E11: 0 | F11: 0 | G11: 0 | H11: 1 | I11: Blocked | J11: 28/09/2026 | K11: Session creation failed; configured Android device was not connected/visible to Appium.
A12: ACME Demo | B12: WebdriverIO + Appium | C12: Android Chrome ? Pixel_10_Pro (emulator-5556) | D12: 1 | E12: 0 | F12: 0 | G12: 0 | H12: 1 | I12: Blocked | J12: 28/09/2026 | K12: Session creation failed; configured Android device was not connected/visible to Appium.
A13: ACME Demo | B13: WebdriverIO + Appium | C13: Android Chrome ? Pixel_6 (emulator-5558) | D13: 1 | E13: 0 | F13: 0 | G13: 0 | H13: 1 | I13: Blocked | J13: 28/09/2026 | K13: Session creation failed; configured Android device was not connected/visible to Appium.
A14: ACME Demo | B14: WebdriverIO + Appium total | C14: Three configured Android emulators | D14: 3 | E14: 0 | F14: 0 | G14: 0 | H14: 3 | I14: Blocked | J14: 28/09/2026 | K14: No test reached the application; all device sessions were blocked by device availability.
A15: ACME Demo | B15: Cucumber mobile BDD | C15: Android Chrome ? Pixel_10_Pro_Fold (emulator-5554) | D15: 1 | E15: 0 | F15: 0 | G15: 0 | H15: 0 | I15: Not Run | K15: Mobile BDD command was not reached in the recorded run.
A16: ACME Demo | B16: Cucumber mobile BDD | C16: Android Chrome ? Pixel_10_Pro (emulator-5556) | D16: 1 | E16: 0 | F16: 0 | G16: 0 | H16: 0 | I16: Not Run | K16: Mobile BDD command was not reached in the recorded run.
A17: ACME Demo | B17: Cucumber mobile BDD | C17: Android Chrome ? Pixel_6 (emulator-5558) | D17: 1 | E17: 0 | F17: 0 | G17: 0 | H17: 0 | I17: Not Run | K17: Mobile BDD command was not reached in the recorded run.
A18: ACME Demo | B18: Cucumber mobile BDD total | C18: Three configured Android emulators | D18: 3 | E18: 0 | F18: 0 | G18: 0 | H18: 0 | I18: Not Run | K18: No mobile BDD result is claimed.
A19: ParaBank | B19: ParaBank Android/platform matrix | C19: Mobile viewport / Android matrix | D19: 77 | E19: 0 | F19: 0 | G19: 0 | H19: 0 | I19: Not Run | K19: Matrix runner is configured but was not executed in this session.
A20: ParaBank | B20: Playwright (single worker rerun) | C20: Desktop Chromium | D20: 77 | E20: 73 | F20: 27 | G20: 46 | H20: 4 | I20: Completed with rate-limit errors | J20: 28/09/2026 | K20: Later serial rerun summary: 27 passed, 46 failed, 4 skipped; shared public demo responses included HTTP 429/Cloudflare 1015. Treat these results as environment-limited.
A21: ParaBank | B21: Playwright headed full acceptance | C21: Desktop Chromium | D21: 144 | E21: 144 | F21: 133 | G21: 11 | H21: 0 | I21: Completed; expected product gaps | J21: 07/10/2026 | K21: Isolated target. 11 known application validation/ordering gaps; zero unexpected automation failures.
A22: ParaBank | B22: Day 9 cross-channel suite | C22: Headed Chromium | D22: 15 | E22: 15 | F22: 15 | G22: 0 | H22: 0 | I22: Passed | J22: 07/10/2026 | K22: All 15 channel, responsive, accessibility-reporting and mocked PayID cases passed.
A23: ParaBank | B23: Day 9 cross-channel suite | C23: Headed Firefox | D23: 15 | E23: 15 | F23: 15 | G23: 0 | H23: 0 | I23: Passed | J23: 07/10/2026 | K23: 15/15 passed in isolated headed Firefox run.
A24: ParaBank | B24: Day 9 cross-channel suite | C24: Headed mobile viewport 390x844 | D24: 15 | E24: 15 | F24: 15 | G24: 0 | H24: 0 | I24: Passed | J24: 07/10/2026 | K24: 15/15 passed.
A25: ParaBank | B25: REST/SOAP API suite | C25: API only (no browser) | D25: 22 | E25: 22 | F25: 22 | G25: 0 | H25: 0 | I25: Passed | J25: 07/10/2026 | K25: 22/22 passed; REST, SOAP parity and API E2E.
A26: ParaBank | B26: Gherkin feature | C26: Headed Chromium | D26: 4 | E26: 4 | F26: 4 | G26: 0 | H26: 0 | I26: Passed | J26: 07/10/2026 | K26: 4 scenarios and 29 steps passed.
A27: ParaBank | B27: Day 10 three-run stability | C27: Desktop Chromium | D27: 432 | E27: 432 | F27: 399 | G27: 33 | H27: 0 | I27: Passed; zero flaky | J27: 07/10/2026 | K27: Three x 144 tests. 33 expected application gaps; zero unexpected, skipped or flaky.
